malix/__init__.py
malix/client.py
malix/utils/Methods.py
malix/utils/__init__.py
malix/utils/attributes.py
malix/utils/exceptions.py
malix/utils/headers.py
malix/utils/jwtoken.py
malix_swain-0.0.5.dist-info/LICENSE
malix_swain-0.0.5.dist-info/METADATA
malix_swain-0.0.5.dist-info/WHEEL
malix_swain-0.0.5.dist-info/top_level.txt
malix_swain-0.0.5.dist-info/RECORD
