Metadata-Version: 2.1
Name: malix-swain
Version: 0.0.5
Summary: An api for generating disposable mails.
Home-page: https://github.com/sunilswain/malix
Author: champsunil
Keywords: temp mail,fake mail,disposable email,api.mail.tm
Classifier: Programming Language :: Python :: 3
Classifier: License :: OSI Approved :: MIT License
Classifier: Operating System :: OS Independent
Requires-Python: >=3.6
License-File: LICENSE
Requires-Dist: requests
